README.md
jarpyvscode/__init__.py
jarpyvscode/__main__.py
jarpyvscode/adaptions.py
jarpyvscode/assets.py
jarpyvscode/constants.py
jarpyvscode/core.py
jarpyvscode/document.py
jarpyvscode/environment.py
jarpyvscode/insiders.py
jarpyvscode/jsonutils.py
jarpyvscode/log.py
jarpyvscode/log.pyi
jarpyvscode/message_and_dialog.py
jarpyvscode/paths.py
jarpyvscode/project.py
jarpyvscode/projects/__init__.py
jarpyvscode/projects/baseproject.py
jarpyvscode/projects/pythonproject.py
jarpyvscode/strings.py
jarpyvscode/usersettings.py
jarpyvscode/utils.py
jarpyvscode/venvs.py
jarpyvscode/vsce.py
jarpyvscode/vscode.json
jarpyvscode/workspace.py
tests/.gitkeep
tests/README.md
tests/__init__.py
tests/conftest.py
tests/test_log.py
tests/test_paths.py
tests/test_project.py
tests/test_pythonproject.py
tests/test_strings.py
tests/test_usersettings.py
tests/test_utils.py
tests/test_workspace.py
jarpyvscode-0.4.8.dist-info/WHEEL
jarpyvscode-0.4.8.dist-info/METADATA
jarpyvscode-0.4.8.dist-info/RECORD
