Metadata-Version: 2.1
Name: jarpyvscode
Version: 0.4.8
Summary: Python backend for Jamil Raichouni's personal Visual Studio Code Extension jamilraichouni.jarpyvscode
Home-page: https://gitlab.com/jar1/jarpyvscode
License: MIT
Author: Jamil André RAICHOUNI
Author-email: raichouni@gmail.com
Maintainer: Jamil André RAICHOUNI
Maintainer-email: raichouni@gmail.com
Requires-Python: >=3.9.7,<4.0
Classifier: License :: OSI Approved :: MIT License
Classifier: Programming Language :: Python :: 3
Classifier: Programming Language :: Python :: 3.10
Requires-Dist: click
Requires-Dist: cookiecutter
Requires-Dist: json5
Requires-Dist: loguru
Requires-Dist: pandas
Requires-Dist: psutil
Project-URL: Documentation, https://jar1.gitlab.io/jarpyvscode
Project-URL: Repository, https://gitlab.com/jar1/jarpyvscode
